singa_easy/__init__.py
singa_easy/__pycache__/__init__.cpython-37.pyc
singa_easy/datasets/TorchImageDataset.py
singa_easy/datasets/__init__.py
singa_easy/datasets/__pycache__/TorchImageDataset.cpython-37.pyc
singa_easy/datasets/__pycache__/__init__.cpython-37.pyc
singa_easy/models/TorchModel.py
singa_easy/models/nni_TorchModel.py
singa_easy/models/__pycache__/TorchModel.cpython-37.pyc
singa_easy/models/__pycache__/nni_TorchModel.cpython-37.pyc
singa_easy/modules/__init__.py
singa_easy/modules/mod.py
singa_easy/modules/__pycache__/__init__.cpython-37.pyc
singa_easy/modules/__pycache__/mod.cpython-37.pyc
singa_easy/modules/explanations/__init__.py
singa_easy/modules/explanations/explanation.py
singa_easy/modules/explanations/__pycache__/__init__.cpython-37.pyc
singa_easy/modules/explanations/gradcam/__init__.py
singa_easy/modules/explanations/gradcam/extractor.py
singa_easy/modules/explanations/gradcam/gradcam.py
singa_easy/modules/explanations/gradcam/util.py
singa_easy/modules/explanations/gradcam/__pycache__/__init__.cpython-37.pyc
singa_easy/modules/explanations/gradcam/__pycache__/extractor.cpython-37.pyc
singa_easy/modules/explanations/gradcam/__pycache__/gradcam.cpython-37.pyc
singa_easy/modules/explanations/lime/__init__.py
singa_easy/modules/explanations/lime/lime.py
singa_easy/modules/explanations/lime/__pycache__/__init__.cpython-37.pyc
singa_easy/modules/explanations/lime/__pycache__/lime.cpython-37.pyc
singa_easy/modules/explanations/maskmap/__init__.py
singa_easy/modules/explanations/maskmap/maskmap.py
singa_easy/modules/explanations/maskmap/misc_functions.py
singa_easy/modules/explanations/maskmap/util.py
singa_easy/modules/mod_driftadapt/__init__.py
singa_easy/modules/mod_driftadapt/label_drift.py
singa_easy/modules/mod_driftadapt/__pycache__/__init__.cpython-37.pyc
singa_easy/modules/mod_driftadapt/__pycache__/label_drift.cpython-37.pyc
singa_easy/modules/mod_gmreg/__init__.py
singa_easy/modules/mod_gmreg/gm_prior_optimizer_pytorch.py
singa_easy-0.4.7.dist-info/LICENSE
singa_easy-0.4.7.dist-info/METADATA
singa_easy-0.4.7.dist-info/NOTICE
singa_easy-0.4.7.dist-info/WHEEL
singa_easy-0.4.7.dist-info/top_level.txt
singa_easy-0.4.7.dist-info/RECORD
