Metadata-Version: 2.1
Name: singa-easy
Version: 0.4.7
Summary: The SINGA-EASY
Home-page: https://github.com/nusdbsystem/singa-easy.git
Author: UNKNOWN
Author-email: UNKNOWN
License: Apache
Platform: UNKNOWN
Requires-Dist: torch (==1.3.1)
Requires-Dist: torchvision (==0.4.2)
Requires-Dist: matplotlib (==3.2.1)
Requires-Dist: lime (==0.2.0.0)
Requires-Dist: tqdm (==4.45.0)
Requires-Dist: numpy (==1.14.5)
